transformation/SignalTransformation.py
transformation/__init__.py
transformation/images/CannyEdgeDetection.py
transformation/images/ImageTransformation.py
transformation/images/Normalize.py
transformation/images/__init__.py
transformation/images/convolution/Convolution.py
transformation/images/convolution/Kernel.py
transformation/images/convolution/StandardConvolution.py
transformation/images/convolution/__init__.py
transformation/images/convolution/edgedetection/EdgeDetection.py
transformation/images/convolution/edgedetection/HorizontalEdgeDetection.py
transformation/images/convolution/edgedetection/HorizontalSobel.py
transformation/images/convolution/edgedetection/Sobel.py
transformation/images/convolution/edgedetection/SobelProcessing.py
transformation/images/convolution/edgedetection/VerticalSobel.py
transformation/images/convolution/edgedetection/VerticialEdgeDetection.py
transformation/images/convolution/edgedetection/__init__.py
transformation/images/convolution/pooling/MaxPooling.py
transformation/images/convolution/pooling/Pooling.py
transformation/images/convolution/pooling/ThresholdPooling.py
transformation/images/convolution/pooling/__init__.py
transformation/images/convolution/supression/NonMaximumSuppression.py
transformation/images/convolution/supression/Suppression.py
transformation/images/convolution/supression/__init__.py
transformation/images/filter/Filter.py
transformation/images/filter/Greyscale.py
transformation/images/filter/__init__.py
transformation/images/mutator/Collage.py
transformation/images/mutator/ColorClassifier.py
transformation/images/mutator/Mutator.py
transformation/images/mutator/Pixelator.py
transformation/images/mutator/RandomReorganizer.py
transformation/images/mutator/__init__.py
SignalProcessor_CraigR8806-0.0.8.dist-info/LICENSE
SignalProcessor_CraigR8806-0.0.8.dist-info/METADATA
SignalProcessor_CraigR8806-0.0.8.dist-info/WHEEL
SignalProcessor_CraigR8806-0.0.8.dist-info/top_level.txt
SignalProcessor_CraigR8806-0.0.8.dist-info/RECORD
